piped/__init__.py
piped/__main__.py
piped/channel.py
piped/comment.py
piped/exceptions.py
piped/fetcher.py
piped/playlist.py
piped/server.py
piped/stream.py
piped/video.py
piped.py-0.2.0.dist-info/LICENCE
piped.py-0.2.0.dist-info/METADATA
piped.py-0.2.0.dist-info/WHEEL
piped.py-0.2.0.dist-info/top_level.txt
piped.py-0.2.0.dist-info/RECORD
