Metadata-Version: 2.1
Name: piped.py
Version: 0.2.0
Summary: API wrapper for Piped written in Python.
Author: t3tra
Author-email: t3tra <admin@t3tra.net>
License: MIT
Project-URL: Homepage, https://github.com/t3tra-dev/piped.py
Project-URL: Issues, https://github.com/t3tra-dev/piped.py/issues
Classifier: Programming Language :: Python :: 3
Classifier: License :: OSI Approved :: MIT License
Classifier: Operating System :: OS Independent
Requires-Python: >=3.8
License-File: LICENCE
